{
  "title": "Project Chimera – Executive Status",
  "subtitle": "Enterprise Platform Modernization Initiative",
  "backlogLink": "https://dev.azure.com/contoso/chimera/_backlogs",
  "currentMonth": "April 2026",
  "months": ["Jan 2026", "Feb 2026", "Mar 2026", "Apr 2026", "May 2026", "Jun 2026"],
  "timeline": {
    "startDate": "2026-01-01",
    "endDate": "2026-06-30",
    "nowDate": "2026-04-13",
    "tracks": [
      {
        "id": "platform",
        "label": "Platform",
        "color": "#0078D4",
        "milestones": [
          { "date": "2026-01-15", "label": "Kickoff", "type": "completed" },
          { "date": "2026-02-28", "label": "Architecture Review", "type": "completed" },
          { "date": "2026-03-31", "label": "MVP Feature Complete", "type": "completed" },
          { "date": "2026-04-15", "label": "Beta Launch", "type": "inprogress" },
          { "date": "2026-05-30", "label": "GA Release", "type": "upcoming" }
        ]
      },
      {
        "id": "data",
        "label": "Data",
        "color": "#28a745",
        "milestones": [
          { "date": "2026-02-01", "label": "Schema Design", "type": "completed" },
          { "date": "2026-03-15", "label": "Migration Scripts", "type": "completed" },
          { "date": "2026-04-30", "label": "Data Validation", "type": "inprogress" },
          { "date": "2026-06-15", "label": "Cutover", "type": "upcoming" }
        ]
      },
      {
        "id": "security",
        "label": "Security",
        "color": "#dc3545",
        "milestones": [
          { "date": "2026-01-31", "label": "Threat Model", "type": "completed" },
          { "date": "2026-03-20", "label": "Pen Test", "type": "completed" },
          { "date": "2026-05-01", "label": "Compliance Audit", "type": "upcoming" },
          { "date": "2026-06-30", "label": "Certification", "type": "upcoming" }
        ]
      }
    ]
  },
  "heatmap": {
    "shipped": {
      "Jan 2026": ["Identity Provider Migration", "CI/CD Pipeline v2"],
      "Feb 2026": ["API Gateway Setup", "Monitoring Dashboard"],
      "Mar 2026": ["Data Lake Integration", "User Auth Overhaul", "Perf Benchmarks"]
    },
    "inProgress": {
      "Apr 2026": ["Beta Onboarding Flow", "Load Testing Suite", "SDK v3 Preview"]
    },
    "carryover": {
      "Apr 2026": ["Legacy API Deprecation", "Mobile Push Notifications"]
    },
    "blockers": {
      "Apr 2026": ["Vendor SSL Certificate Renewal"]
    }
  }
}